{
  "d_number": "D278522",
  "author": "ErichDonGubler",
  "created_at": "2026-01-09T18:02:39+00:00",
  "events": [
    {
      "ts": "2026-01-09T18:02:39+00:00",
      "actor": "ErichDonGubler",
      "action": "create"
    },
    {
      "ts": "2026-01-09T18:02:40+00:00",
      "actor": "Herald",
      "action": "other"
    },
    {
      "ts": "2026-01-09T18:02:46+00:00",
      "actor": "ErichDonGubler",
      "action": "add-child"
    },
    {
      "ts": "2026-01-09T18:04:02+00:00",
      "actor": "phab-bot",
      "action": "publish"
    },
    {
      "ts": "2026-01-09T18:29:47+00:00",
      "actor": "Harbormaster",
      "action": "other"
    },
    {
      "ts": "2026-01-09T20:40:25+00:00",
      "actor": "aleiserson",
      "action": "accept"
    },
    {
      "ts": "2026-01-09T20:40:26+00:00",
      "actor": "Herald",
      "action": "other"
    },
    {
      "ts": "2026-01-14T01:47:00+00:00",
      "actor": "ErichDonGubler",
      "action": "other"
    },
    {
      "ts": "2026-01-14T02:27:33+00:00",
      "actor": "rFIREFOXAUTOLANDcdb944ea0d1f: Bug 2008734 - fix(webgpu): make early WebGPU feature gating resolve the promise\u2026",
      "action": "other"
    },
    {
      "ts": "2026-01-14T03:44:10+00:00",
      "actor": "pstanciu",
      "action": "reopen"
    },
    {
      "ts": "2026-01-14T03:44:10+00:00",
      "actor": "pstanciu",
      "action": "other"
    },
    {
      "ts": "2026-01-23T18:46:20+00:00",
      "actor": "ErichDonGubler",
      "action": "update-diff"
    },
    {
      "ts": "2026-01-23T19:04:01+00:00",
      "actor": "Harbormaster",
      "action": "other"
    },
    {
      "ts": "2026-01-23T19:14:01+00:00",
      "actor": "ErichDonGubler",
      "action": "update-diff"
    },
    {
      "ts": "2026-01-23T19:33:07+00:00",
      "actor": "Harbormaster",
      "action": "other"
    },
    {
      "ts": "2026-01-23T20:57:29+00:00",
      "actor": "rFIREFOXAUTOLAND0add216197b6: Bug 2008734 - fix(webgpu): make early WebGPU feature gating resolve the promise\u2026",
      "action": "other"
    },
    {
      "ts": "2026-01-23T22:12:23+00:00",
      "actor": "pstanciu",
      "action": "reopen"
    },
    {
      "ts": "2026-01-23T22:12:23+00:00",
      "actor": "pstanciu",
      "action": "other"
    },
    {
      "ts": "2026-01-24T21:19:43+00:00",
      "actor": "ErichDonGubler",
      "action": "update-diff"
    },
    {
      "ts": "2026-01-24T21:50:35+00:00",
      "actor": "Harbormaster",
      "action": "other"
    },
    {
      "ts": "2026-01-25T12:35:00+00:00",
      "actor": "Harbormaster",
      "action": "other"
    },
    {
      "ts": "2026-02-23T14:12:42+00:00",
      "actor": "ErichDonGubler",
      "action": "other"
    },
    {
      "ts": "2026-02-23T14:47:11+00:00",
      "actor": "ErichDonGubler",
      "action": "other"
    },
    {
      "ts": "2026-03-18T18:07:11+00:00",
      "actor": "ErichDonGubler",
      "action": "other"
    },
    {
      "ts": "2026-03-18T18:46:40+00:00",
      "actor": "ErichDonGubler",
      "action": "other"
    }
  ],
  "time_to_react_seconds": 9466,
  "time_to_accept_seconds": 9466
}