{
  "d_number": "D281164",
  "author": "jnicol",
  "created_at": "2026-01-30T12:18:11+00:00",
  "events": [
    {
      "ts": "2026-01-30T12:18:11+00:00",
      "actor": "jnicol",
      "action": "create"
    },
    {
      "ts": "2026-01-30T12:18:12+00:00",
      "actor": "Herald",
      "action": "other"
    },
    {
      "ts": "2026-01-30T12:18:18+00:00",
      "actor": "jnicol",
      "action": "add-child"
    },
    {
      "ts": "2026-01-30T12:20:39+00:00",
      "actor": "phab-bot",
      "action": "publish"
    },
    {
      "ts": "2026-01-30T12:21:05+00:00",
      "actor": "jnicol",
      "action": "update-diff"
    },
    {
      "ts": "2026-01-30T12:40:07+00:00",
      "actor": "Harbormaster",
      "action": "other"
    },
    {
      "ts": "2026-01-30T17:19:51+00:00",
      "actor": "lsalzman",
      "action": "accept"
    },
    {
      "ts": "2026-01-30T17:19:51+00:00",
      "actor": "Herald",
      "action": "other"
    },
    {
      "ts": "2026-01-30T21:40:33+00:00",
      "actor": "jnicol",
      "action": "other"
    },
    {
      "ts": "2026-01-30T21:56:02+00:00",
      "actor": "rFIREFOXAUTOLAND9ef79690b167: Bug 2013484 - Allow using AndroidHarwareBuffer without\u2026",
      "action": "other"
    },
    {
      "ts": "2026-02-23T15:07:53+00:00",
      "actor": "jnicol",
      "action": "other"
    },
    {
      "ts": "2026-03-18T19:10:29+00:00",
      "actor": "jnicol",
      "action": "other"
    }
  ],
  "time_to_react_seconds": 18100,
  "time_to_accept_seconds": 18100
}