{
  "d_number": "D281695",
  "author": "hiro",
  "created_at": null,
  "events": [
    {
      "ts": "2026-02-03T23:10:03+00:00",
      "actor": "hiro",
      "action": "other"
    },
    {
      "ts": "2026-02-03T23:10:04+00:00",
      "actor": "Herald",
      "action": "other"
    },
    {
      "ts": "2026-02-03T23:10:08+00:00",
      "actor": "hiro",
      "action": "add-child"
    },
    {
      "ts": "2026-02-03T23:11:11+00:00",
      "actor": "phab-bot",
      "action": "change-visibility"
    },
    {
      "ts": "2026-02-03T23:11:11+00:00",
      "actor": "Herald",
      "action": "other"
    },
    {
      "ts": "2026-02-03T23:44:11+00:00",
      "actor": "Harbormaster",
      "action": "other"
    },
    {
      "ts": "2026-02-04T07:51:06+00:00",
      "actor": "whimboo",
      "action": "other"
    },
    {
      "ts": "2026-02-04T08:07:58+00:00",
      "actor": "hiro",
      "action": "request-review"
    },
    {
      "ts": "2026-02-04T08:10:24+00:00",
      "actor": "hiro",
      "action": "update-diff"
    },
    {
      "ts": "2026-02-04T08:40:14+00:00",
      "actor": "Harbormaster",
      "action": "other"
    },
    {
      "ts": "2026-02-04T09:01:51+00:00",
      "actor": "whimboo",
      "action": "comment"
    },
    {
      "ts": "2026-02-04T21:57:31+00:00",
      "actor": "botond",
      "action": "accept"
    },
    {
      "ts": "2026-02-04T22:01:55+00:00",
      "actor": "hiro",
      "action": "update-diff"
    },
    {
      "ts": "2026-02-04T22:13:37+00:00",
      "actor": "hiro",
      "action": "mark-done"
    },
    {
      "ts": "2026-02-04T22:16:03+00:00",
      "actor": "Harbormaster",
      "action": "other"
    },
    {
      "ts": "2026-02-05T00:08:18+00:00",
      "actor": "rFIREFOXAUTOLANDd828cf5e65df: Bug 1962355 - Add a pref to allow scroll amount larger than a page on a single\u2026",
      "action": "other"
    },
    {
      "ts": "2026-02-23T15:21:27+00:00",
      "actor": "hiro",
      "action": "other"
    },
    {
      "ts": "2026-03-18T19:26:41+00:00",
      "actor": "hiro",
      "action": "other"
    }
  ],
  "time_to_react_seconds": null,
  "time_to_accept_seconds": null
}