{
  "d_number": "D301068",
  "author": "nkulatova",
  "created_at": null,
  "events": [
    {
      "ts": "2026-05-18T13:51:55+00:00",
      "actor": "nkulatova",
      "action": "other"
    },
    {
      "ts": "2026-05-18T13:51:56+00:00",
      "actor": "Herald",
      "action": "other"
    },
    {
      "ts": "2026-05-18T13:52:28+00:00",
      "actor": "nkulatova",
      "action": "request-review"
    },
    {
      "ts": "2026-05-18T13:52:29+00:00",
      "actor": "Herald",
      "action": "add-reviewer",
      "target": "webidl"
    },
    {
      "ts": "2026-05-18T13:53:36+00:00",
      "actor": "phab-bot",
      "action": "change-visibility"
    },
    {
      "ts": "2026-05-18T14:01:15+00:00",
      "actor": "pehrsons",
      "action": "add-reviewer",
      "target": "bwc"
    },
    {
      "ts": "2026-05-18T14:04:12+00:00",
      "actor": "Harbormaster",
      "action": "other"
    },
    {
      "ts": "2026-05-18T14:07:50+00:00",
      "actor": "nkulatova",
      "action": "add-parent"
    },
    {
      "ts": "2026-05-18T14:55:30+00:00",
      "actor": "nkulatova",
      "action": "retitle"
    },
    {
      "ts": "2026-05-18T15:17:49+00:00",
      "actor": "nkulatova",
      "action": "update-diff"
    },
    {
      "ts": "2026-05-18T15:45:12+00:00",
      "actor": "nkulatova",
      "action": "update-diff"
    },
    {
      "ts": "2026-05-18T15:46:18+00:00",
      "actor": "nkulatova",
      "action": "comment"
    },
    {
      "ts": "2026-05-18T15:49:18+00:00",
      "actor": "Harbormaster",
      "action": "other"
    },
    {
      "ts": "2026-05-18T16:14:23+00:00",
      "actor": "reviewbot",
      "action": "other"
    },
    {
      "ts": "2026-05-18T16:14:30+00:00",
      "actor": "Harbormaster",
      "action": "other"
    },
    {
      "ts": "2026-05-18T16:42:36+00:00",
      "actor": "pehrsons",
      "action": "comment"
    },
    {
      "ts": "2026-05-18T17:04:50+00:00",
      "actor": "bwc",
      "action": "request-changes"
    },
    {
      "ts": "2026-05-19T09:27:21+00:00",
      "actor": "nkulatova",
      "action": "request-review"
    },
    {
      "ts": "2026-05-19T09:29:04+00:00",
      "actor": "nkulatova",
      "action": "mark-done"
    },
    {
      "ts": "2026-05-19T09:58:52+00:00",
      "actor": "Harbormaster",
      "action": "other"
    },
    {
      "ts": "2026-05-19T14:50:25+00:00",
      "actor": "smaug",
      "action": "accept"
    },
    {
      "ts": "2026-05-19T16:39:09+00:00",
      "actor": "nkulatova",
      "action": "update-diff"
    },
    {
      "ts": "2026-05-19T16:40:28+00:00",
      "actor": "nkulatova",
      "action": "comment"
    },
    {
      "ts": "2026-05-19T16:41:54+00:00",
      "actor": "nkulatova",
      "action": "other"
    },
    {
      "ts": "2026-05-19T17:21:39+00:00",
      "actor": "Harbormaster",
      "action": "other"
    },
    {
      "ts": "2026-05-19T17:31:48+00:00",
      "actor": "bwc",
      "action": "comment"
    },
    {
      "ts": "2026-05-19T17:32:28+00:00",
      "actor": "bwc",
      "action": "accept"
    },
    {
      "ts": "2026-05-19T19:28:16+00:00",
      "actor": "pehrsons",
      "action": "comment"
    },
    {
      "ts": "2026-05-24T07:12:23+00:00",
      "actor": "philipp.hancke",
      "action": "other"
    },
    {
      "ts": "2026-05-24T11:25:29+00:00",
      "actor": "philipp.hancke",
      "action": "other"
    },
    {
      "ts": "2026-05-25T17:24:54+00:00",
      "actor": "bwc",
      "action": "request-changes"
    },
    {
      "ts": "2026-05-25T18:04:55+00:00",
      "actor": "nkulatova",
      "action": "comment"
    },
    {
      "ts": "2026-05-25T18:10:17+00:00",
      "actor": "bwc",
      "action": "comment"
    },
    {
      "ts": "2026-05-26T16:21:17+00:00",
      "actor": "nkulatova",
      "action": "request-review"
    },
    {
      "ts": "2026-05-26T16:50:59+00:00",
      "actor": "Harbormaster",
      "action": "other"
    },
    {
      "ts": "2026-05-26T17:10:59+00:00",
      "actor": "smaug",
      "action": "accept"
    },
    {
      "ts": "2026-05-26T17:31:42+00:00",
      "actor": "bwc",
      "action": "accept"
    },
    {
      "ts": "2026-06-01T13:32:59+00:00",
      "actor": "rFIREFOXAUTOLAND3dff814f6a32: Bug 2019389 - Implement RTCTransportStats.tlsVersion/dtlsCipher/srtpCipher\u2026",
      "action": "other"
    }
  ],
  "time_to_react_seconds": null,
  "time_to_accept_seconds": null
}