{
  "d_number": "D302234",
  "author": "wery222",
  "created_at": "2026-05-24T19:26:00+00:00",
  "events": [
    {
      "ts": "2026-05-24T19:26:00+00:00",
      "actor": "wery222",
      "action": "create"
    },
    {
      "ts": "2026-05-24T19:26:02+00:00",
      "actor": "Herald",
      "action": "other"
    },
    {
      "ts": "2026-05-24T19:26:08+00:00",
      "actor": "phab-bot",
      "action": "publish"
    },
    {
      "ts": "2026-05-24T19:26:08+00:00",
      "actor": "Herald",
      "action": "other"
    },
    {
      "ts": "2026-05-24T19:57:02+00:00",
      "actor": "Harbormaster",
      "action": "other"
    },
    {
      "ts": "2026-05-24T21:28:47+00:00",
      "actor": "botond",
      "action": "comment"
    },
    {
      "ts": "2026-05-25T08:19:26+00:00",
      "actor": "wery222",
      "action": "update-diff"
    },
    {
      "ts": "2026-05-25T08:21:39+00:00",
      "actor": "wery222",
      "action": "update-diff"
    },
    {
      "ts": "2026-05-25T08:23:07+00:00",
      "actor": "wery222",
      "action": "comment"
    },
    {
      "ts": "2026-05-25T08:51:11+00:00",
      "actor": "Harbormaster",
      "action": "other"
    },
    {
      "ts": "2026-05-25T08:55:10+00:00",
      "actor": "Harbormaster",
      "action": "other"
    },
    {
      "ts": "2026-05-26T04:18:17+00:00",
      "actor": "botond",
      "action": "add-parent"
    },
    {
      "ts": "2026-05-26T04:26:01+00:00",
      "actor": "botond",
      "action": "request-changes"
    },
    {
      "ts": "2026-05-26T21:54:45+00:00",
      "actor": "wery222",
      "action": "request-review"
    },
    {
      "ts": "2026-05-26T21:56:07+00:00",
      "actor": "wery222",
      "action": "comment"
    },
    {
      "ts": "2026-05-26T22:33:08+00:00",
      "actor": "Harbormaster",
      "action": "other"
    },
    {
      "ts": "2026-05-27T02:10:29+00:00",
      "actor": "botond",
      "action": "comment"
    },
    {
      "ts": "2026-05-27T02:10:46+00:00",
      "actor": "botond",
      "action": "accept"
    },
    {
      "ts": "2026-05-27T02:13:33+00:00",
      "actor": "botond",
      "action": "comment"
    },
    {
      "ts": "2026-05-27T04:09:45+00:00",
      "actor": "rFIREFOXAUTOLAND31bacaa9765b: Bug 2041151 - Add a gtest for bug 1536520 - r=botond",
      "action": "other"
    }
  ],
  "time_to_react_seconds": 7367,
  "time_to_accept_seconds": 197086
}