{
  "d_number": "D304270",
  "author": "alwu",
  "created_at": "2026-06-02T21:23:31+00:00",
  "events": [
    {
      "ts": "2026-06-02T21:23:31+00:00",
      "actor": "alwu",
      "action": "create"
    },
    {
      "ts": "2026-06-02T21:23:33+00:00",
      "actor": "Herald",
      "action": "other"
    },
    {
      "ts": "2026-06-02T21:23:38+00:00",
      "actor": "alwu",
      "action": "add-child"
    },
    {
      "ts": "2026-06-02T21:25:21+00:00",
      "actor": "phab-bot",
      "action": "publish"
    },
    {
      "ts": "2026-06-02T21:25:21+00:00",
      "actor": "Herald",
      "action": "add-reviewer",
      "target": "webrtc-reviewers"
    },
    {
      "ts": "2026-06-02T22:27:02+00:00",
      "actor": "bwc",
      "action": "accept"
    },
    {
      "ts": "2026-06-02T22:33:50+00:00",
      "actor": "reviewbot",
      "action": "other"
    },
    {
      "ts": "2026-06-02T22:33:56+00:00",
      "actor": "Harbormaster",
      "action": "other"
    },
    {
      "ts": "2026-06-03T10:45:55+00:00",
      "actor": "pehrsons",
      "action": "other"
    },
    {
      "ts": "2026-06-03T19:56:08+00:00",
      "actor": "alwu",
      "action": "update-diff"
    },
    {
      "ts": "2026-06-03T20:17:43+00:00",
      "actor": "Harbormaster",
      "action": "other"
    },
    {
      "ts": "2026-06-03T21:49:31+00:00",
      "actor": "alwu",
      "action": "other"
    },
    {
      "ts": "2026-06-03T21:50:45+00:00",
      "actor": "alwu",
      "action": "update-diff"
    },
    {
      "ts": "2026-06-03T21:54:57+00:00",
      "actor": "alwu",
      "action": "mark-done"
    },
    {
      "ts": "2026-06-03T22:21:59+00:00",
      "actor": "Harbormaster",
      "action": "other"
    },
    {
      "ts": "2026-06-04T01:50:35+00:00",
      "actor": "alwu",
      "action": "update-diff"
    },
    {
      "ts": "2026-06-04T02:26:03+00:00",
      "actor": "Harbormaster",
      "action": "other"
    },
    {
      "ts": "2026-06-04T03:25:28+00:00",
      "actor": "alwu",
      "action": "update-diff"
    },
    {
      "ts": "2026-06-04T03:55:00+00:00",
      "actor": "Harbormaster",
      "action": "other"
    },
    {
      "ts": "2026-06-04T13:32:20+00:00",
      "actor": "abutkovits",
      "action": "reopen"
    },
    {
      "ts": "2026-06-04T13:32:24+00:00",
      "actor": "abutkovits",
      "action": "other"
    },
    {
      "ts": "2026-06-04T17:19:16+00:00",
      "actor": "alwu",
      "action": "update-diff"
    },
    {
      "ts": "2026-06-04T17:55:58+00:00",
      "actor": "Harbormaster",
      "action": "other"
    },
    {
      "ts": "2026-06-04T21:20:25+00:00",
      "actor": "rFIREFOXAUTOLAND7d440212b618: Bug 2044124 - Part 19: Use MOZ_LOG_FMT in webrtc MOZ_LOG-based logs. r=webrtc\u2026",
      "action": "other"
    }
  ],
  "time_to_react_seconds": 3811,
  "time_to_accept_seconds": 3811
}